License.txt
README.md
setup.py
o2des/action.py
o2des/assets.py
o2des/event.py
o2des/hour_counter.py
o2des/sandbox.py
o2des.egg-info/PKG-INFO
o2des.egg-info/SOURCES.txt
o2des.egg-info/dependency_links.txt
o2des.egg-info/top_level.txt
standard/generator.py
standard/load.py
standard/queue.py
standard/server.py